gcoin_rpc-0.4.1.dist-info/DESCRIPTION.rst
gcoin_rpc-0.4.1.dist-info/METADATA
gcoin_rpc-0.4.1.dist-info/RECORD
gcoin_rpc-0.4.1.dist-info/WHEEL
gcoin_rpc-0.4.1.dist-info/metadata.json
gcoin_rpc-0.4.1.dist-info/top_level.txt
gcoinrpc/__init__.py
gcoinrpc/config.py
gcoinrpc/connection.py
gcoinrpc/data.py
gcoinrpc/exceptions.py
gcoinrpc/proxy.py
gcoinrpc/util.py
